deep_filter.py
deep_filter-1.0.1.dist-info/WHEEL
deep_filter-1.0.1.dist-info/METADATA
deep_filter-1.0.1.dist-info/RECORD
