Metadata-Version: 2.1
Name: deep-filter
Version: 1.0.1
Summary: Removes values from nested dicts and lists
Home-page: https://github.com/probablykasper/deep-filter
Keywords: filter,remove,nested,recursively,delete,dicts,lists
Author: kasper.space
Requires-Python: >=3.5,<4.0
Classifier: Programming Language :: Python :: 3
Classifier: Programming Language :: Python :: 3.5
Classifier: Programming Language :: Python :: 3.6
Classifier: Programming Language :: Python :: 3.7
Classifier: Programming Language :: Python :: 3.8
Project-URL: Repository, https://github.com/probablykasper/deep-filter
